odoo/addons/account_payment_terminal/README.rst
odoo/addons/account_payment_terminal/__init__.py
odoo/addons/account_payment_terminal/__manifest__.py
odoo/addons/account_payment_terminal/i18n/account_payment_terminal.pot
odoo/addons/account_payment_terminal/i18n/es.po
odoo/addons/account_payment_terminal/i18n/it.po
odoo/addons/account_payment_terminal/models/__init__.py
odoo/addons/account_payment_terminal/models/account_journal.py
odoo/addons/account_payment_terminal/models/account_payment_terminal.py
odoo/addons/account_payment_terminal/models/oca_payment_terminal_form_mixin.py
odoo/addons/account_payment_terminal/readme/CONFIGURE.rst
odoo/addons/account_payment_terminal/readme/CONTRIBUTORS.rst
odoo/addons/account_payment_terminal/readme/DESCRIPTION.rst
odoo/addons/account_payment_terminal/readme/USAGE.rst
odoo/addons/account_payment_terminal/security/account_payment_terminal.xml
odoo/addons/account_payment_terminal/static/description/icon.png
odoo/addons/account_payment_terminal/static/description/index.html
odoo/addons/account_payment_terminal/static/src/js/views/payment_terminal_form/payment_terminal_form_controller.js
odoo/addons/account_payment_terminal/static/src/js/views/payment_terminal_form/payment_terminal_form_view.js
odoo/addons/account_payment_terminal/views/account_journal.xml
odoo/addons/account_payment_terminal/views/account_payment_terminal.xml
odoo/addons/account_payment_terminal/views/oca_payment_terminal_form_mixin.xml
odoo/addons/account_payment_terminal/views/webclient_templates.xml
odoo/addons/account_payment_terminal/wizards/__init__.py
odoo/addons/account_payment_terminal/wizards/account_payment_register.py
odoo/addons/account_payment_terminal/wizards/account_payment_register.xml
odoo14_addon_account_payment_terminal-14.0.1.0.1.dev13.dist-info/METADATA
odoo14_addon_account_payment_terminal-14.0.1.0.1.dev13.dist-info/WHEEL
odoo14_addon_account_payment_terminal-14.0.1.0.1.dev13.dist-info/top_level.txt
odoo14_addon_account_payment_terminal-14.0.1.0.1.dev13.dist-info/RECORD
