Metadata-Version: 2.1
Name: odoo14-addon-account_payment_terminal
Version: 14.0.1.0.1.dev13
Summary: This addon allows to pay invoices using payment terminal
Home-page: https://github.com/OCA/account-payment
Author: ACSONE SA/NV, Odoo Community Association (OCA)
Author-email: support@odoo-community.org
License: AGPL-3
Classifier: Programming Language :: Python
Classifier: Framework :: Odoo
Classifier: Framework :: Odoo :: 14.0
Classifier: License :: OSI Approved :: GNU Affero General Public License v3
Requires-Python: >=3.6
Requires-Dist: odoo<14.1dev,>=14.0a
